PythonCodeVault/KerasDatasets.py
PythonCodeVault/TrainTestValSplitter.py
PythonCodeVault/__init__.py
PythonCodeVault/onnxConverter.py
PythonCodeVault-0.0.15.dist-info/METADATA
PythonCodeVault-0.0.15.dist-info/WHEEL
PythonCodeVault-0.0.15.dist-info/top_level.txt
PythonCodeVault-0.0.15.dist-info/RECORD
