Metadata-Version: 2.1
Name: PythonCodeVault
Version: 0.0.15
Summary: My Python Functions
Author: Kevin Fischer
Author-email: <kevinfischer1611@gmail.com>
Keywords: python
Classifier: Development Status :: 1 - Planning
Classifier: Intended Audience :: Developers
Classifier: Programming Language :: Python :: 3
Classifier: Operating System :: Unix
Classifier: Operating System :: MacOS :: MacOS X
Classifier: Operating System :: Microsoft :: Windows
Requires-Dist: tqdm
